Workbook

Sheet KPI Dashboard
A1: 📊 MARKETING CAMPAIGN PERFORMANCE · KPI DASHBOARD · FY 2024
A3: All monetary values in Indian Rupees (₹) · Data source: Campaign Data sheet · Metrics auto-refresh on data change
A5: TOTAL REVENUE | D5: TOTAL SPEND | G5: OVERALL ROAS | J5: TOTAL CLICKS | M5: CONVERSIONS | P5: TOTAL LEADS
A6: =SUMIF('Campaign Data'!U:U,"Completed",'Campaign Data'!N:N) -> 36061200 | D6: =SUMIF('Campaign Data'!U:U,"<>Cancelled",'Campaign Data'!J:J) -> 9560800 | G6: =IFERROR(SUMIF('Campaign Data'!U:U,"Completed",'Campaign Data'!N:N)/SUMIF('Campaign Data'!U:U,"Completed",'Campaign Data'!J:J),0) -> 3.8749234 | J6: =SUM('Campaign Data'!L:L) -> 2459693 | M6: =SUM('Campaign Data'!M:M) -> 171099 | P6: =SUM('Campaign Data'!O:O) -> 335260
A9: Completed Campaigns | D9: All Active | G9: Revenue / Spend | J9: Across All Channels | M9: All Campaigns | P9: Pipeline Generated
A11: QUICK PERFORMANCE INSIGHTS
A12: KPI | B12: Value | C12: Target | D12: vs Target | E12: Status
A13: Total Campaigns Launched | B13: =COUNTA('Campaign Data'!A:A)-1 -> 80 | C13: 100 | D13: =IFERROR(B13-C13,"—") -> -20 | E13: ✅ On Track
A14: Total Budget Allocated (₹) | B14: =SUM('Campaign Data'!I:I) -> 10799700 | C14: 50000000 | D14: =IFERROR(B14-C14,"—") -> -39200300 | E14: ✅ On Track
A15: Overall Budget Utilisation | B15: =IFERROR(SUM('Campaign Data'!J:J)/SUM('Campaign Data'!I:I),0) -> 0.88528385 | C15: 0.9 | D15: =IFERROR(B15-C15,"—") -> -0.01471615 | E15: ✅ On Track
A16: Blended ROAS | B16: =IFERROR(SUM('Campaign Data'!N:N)/SUM('Campaign Data'!J:J),0) -> 3.8848841 | C16: 3.5 | D16: =IFERROR(B16-C16,"—") -> 0.38488411 | E16: ✅ On Track
A17: Total Impressions | B17: =SUM('Campaign Data'!K:K) -> 28449900 | C17: 10000000 | D17: =IFERROR(B17-C17,"—") -> 18449900 | E17: ✅ On Track
A18: Avg Click-Through Rate (%) | B18: =IFERROR(AVERAGE('Campaign Data'!R:R),0) -> 9.4464882 | C18: 5 | D18: =IFERROR(B18-C18,"—") -> 4.4464882 | E18: ✅ On Track
A19: Avg Conversion Rate (%) | B19: =IFERROR(AVERAGE('Campaign Data'!S:S),0) -> 4.2011378 | C19: 3 | D19: =IFERROR(B19-C19,"—") -> 1.2011378 | E19: ✅ On Track
A20: Cost per Conversion (₹) | B20: =IFERROR(SUM('Campaign Data'!J:J)/SUM('Campaign Data'!M:M),0) -> 55.87876 | C20: 500 | D20: =IFERROR(B20-C20,"—") -> -444.12124 | E20: ✅ On Track
A21: Cost per Lead (₹) | B21: =IFERROR(SUM('Campaign Data'!J:J)/SUM('Campaign Data'!O:O),0) -> 28.517568 | C21: 300 | D21: =IFERROR(B21-C21,"—") -> -271.48243 | E21: ✅ On Track
A22: Return on Ad Spend — Email | B22: =IFERROR(SUMIF('Campaign Data'!C:C,"Email",'Campaign Data'!N:N)/SUMIF('Campaign Data'!C:C,"Email",'Campaign Data'!J:J),0) -> 7.889071 | C22: 8 | D22: =IFERROR(B22-C22,"—") -> -0.11092896 | E22: ✅ On Track
A24: 📌 STRATEGIC RECOMMENDATIONS
A25: ▸ Email marketing delivers the highest ROAS — scale budget allocation by 20% in Q1 2025.
A26: ▸ LinkedIn and YouTube show below-average CTR; review creative assets and audience targeting.
A27: ▸ Q4 campaigns (Oct–Dec) consistently outperform — front-load inventory and budget for festive season.
A28: ▸ Conversion objective campaigns show the best cost-per-lead; increase share of spend from 20% → 30%.
A29: ▸ Influencer channel drives high impressions but low CVR; shift to performance-linked contracts.
A30: NAVIGATE: KPI Dashboard · Channel Performance · Monthly Trends · Objective Analysis · Campaign Data

Sheet Campaign Data
A1: Campaign ID | B1: Campaign Name | C1: Channel | D1: Objective | E1: Quarter | F1: Month | G1: Start Date | H1: End Date | I1: Budget (₹) | J1: Spend (₹) | K1: Impressions | L1: Clicks | M1: Conversions | N1: Revenue Generated (₹) | O1: Leads | P1: Cost per Click (₹) | Q1: Cost per Conversion (₹) | R1: CTR (%) | S1: Conv Rate (%) | T1: ROAS | U1: Status
A2: CMP-0001 | B2: SMS Jan 2024 | C2: SMS | D2: Traffic | E2: Q1 | F2: Jan | G2: 2024-01-01 | H2: 2024-01-28 | I2: 23800 | J2: 23800 | K2: 710428 | L2: 252628 | M2: 14475 | N2: 105700 | O2: 43246 | P2: =J2/L2 -> 0.094209668 | Q2: =IFERROR(J2/M2,0) -> 1.6442142 | R2: =L2/K2*100 -> 35.559972 | S2: =IFERROR(M2/L2*100,0) -> 5.7297687 | T2: =N2/J2 -> 4.4411765 | U2: Completed
A3: CMP-0002 | B3: SEO/Organic Jan 2024 | C3: SEO/Organic | D3: Brand Awareness | E3: Q1 | F3: Jan | G3: 2024-01-01 | H3: 2024-01-28 | I3: 75400 | J3: 74600 | K3: 118613 | L3: 6440 | M3: 320 | N3: 638600 | O3: 865 | P3: =J3/L3 -> 11.583851 | Q3: =IFERROR(J3/M3,0) -> 233.125 | R3: =L3/K3*100 -> 5.4294217 | S3: =IFERROR(M3/L3*100,0) -> 4.9689441 | T3: =N3/J3 -> 8.5603217 | U3: Completed
A4: CMP-0003 | B4: Email Jan 2024 | C4: Email | D4: Traffic | E4: Q1 | F4: Jan | G4: 2024-01-01 | H4: 2024-01-28 | I4: 26900 | J4: 24400 | K4: 122363 | L4: 33784 | M4: 4631 | N4: 175400 | O4: 6604 | P4: =J4/L4 -> 0.72223538 | Q4: =IFERROR(J4/M4,0) -> 5.2688404 | R4: =L4/K4*100 -> 27.609653 | S4: =IFERROR(M4/L4*100,0) -> 13.707672 | T4: =N4/J4 -> 7.1885246 | U4: Completed
A5: CMP-0004 | B5: YouTube Jan 2024 | C5: YouTube | D5: Retention | E5: Q1 | F5: Jan | G5: 2024-01-01 | H5: 2024-01-28 | I5: 234300 | J5: 177900 | K5: 649244 | L5: 4674 | M5: 60 | N5: 510600 | O5: 143 | P5: =J5/L5 -> 38.061617 | Q5: =IFERROR(J5/M5,0) -> 2965 | R5: =L5/K5*100 -> 0.71991424 | S5: =IFERROR(M5/L5*100,0) -> 1.283697 | T5: =N5/J5 -> 2.8701518 | U5: Completed
A6: CMP-0005 | B6: LinkedIn Jan 2024 | C6: LinkedIn | D6: Retention | E6: Q1 | F6: Jan | G6: 2024-01-01 | H6: 2024-01-28 | I6: 68900 | J6: 60100 | K6: 21444 | L6: 201 | M6: 2 | N6: 221800 | O6: 2 | P6: =J6/L6 -> 299.00498 | Q6: =IFERROR(J6/M6,0) -> 30050 | R6: =L6/K6*100 -> 0.93732513 | S6: =IFERROR(M6/L6*100,0) -> 0.99502488 | T6: =N6/J6 -> 3.6905158 | U6: Completed
A7: CMP-0006 | B7: Meta Ads Jan 2024 | C7: Meta Ads | D7: Lead Generation | E7: Q1 | F7: Jan | G7: 2024-01-01 | H7: 2024-01-28 | I7: 254700 | J7: 224000 | K7: 76947 | L7: 2008 | M7: 73 | N7: 1073000 | O7: 127 | P7: =J7/L7 -> 111.55378 | Q7: =IFERROR(J7/M7,0) -> 3068.4932 | R7: =L7/K7*100 -> 2.6095884 | S7: =IFERROR(M7/L7*100,0) -> 3.6354582 | T7: =N7/J7 -> 4.7901786 | U7: Completed
A8: CMP-0007 | B8: Email Feb 2024 | C8: Email | D8: Brand Awareness | E8: Q1 | F8: Feb | G8: 2024-02-01 | H8: 2024-02-28 | I8: 58800 | J8: 53400 | K8: 287553 | L8: 80342 | M8: 10653 | N8: 330000 | O8: 15083 | P8: =J8/L8 -> 0.66465858 | Q8: =IFERROR(J8/M8,0) -> 5.0126725 | R8: =L8/K8*100 -> 27.939893 | S8: =IFERROR(M8/L8*100,0) -> 13.259565 | T8: =N8/J8 -> 6.1797753 | U8: Completed
A9: CMP-0008 | B9: Google Ads Feb 2024 | C9: Google Ads | D9: Retention | E9: Q1 | F9: Feb | G9: 2024-02-01 | H9: 2024-02-28 | I9: 203400 | J9: 188500 | K9: 531935 | L9: 37660 | M9: 1389 | N9: 816200 | O9: 3140 | P9: =J9/L9 -> 5.0053107 | Q9: =IFERROR(J9/M9,0) -> 135.70914 | R9: =L9/K9*100 -> 7.0798124 | S9: =IFERROR(M9/L9*100,0) -> 3.6882634 | T9: =N9/J9 -> 4.3299735 | U9: Completed
A10: CMP-0009 | B10: YouTube Feb 2024 | C10: YouTube | D10: Traffic | E10: Q1 | F10: Feb | G10: 2024-02-01 | H10: 2024-02-28 | I10: 169900 | J10: 152300 | K10: 540711 | L10: 3136 | M10: 53 | N10: 565000 | O10: 99 | P10: =J10/L10 -> 48.565051 | Q10: =IFERROR(J10/M10,0) -> 2873.5849 | R10: =L10/K10*100 -> 0.5799771 | S10: =IFERROR(M10/L10*100,0) -> 1.690051 | T10: =N10/J10 -> 3.7097833 | U10: Completed
A11: CMP-0010 | B11: LinkedIn Feb 2024 | C11: LinkedIn | D11: Traffic | E11: Q1 | F11: Feb | G11: 2024-02-01 | H11: 2024-02-28 | I11: 216900 | J11: 192500 | K11: 465099 | L11: 3023 | M11: 47 | N11: 766200 | O11: 114 | P11: =J11/L11 -> 63.678465 | Q11: =IFERROR(J11/M11,0) -> 4095.7447 | R11: =L11/K11*100 -> 0.64996915 | S11: =IFERROR(M11/L11*100,0) -> 1.5547469 | T11: =N11/J11 -> 3.9802597 | U11: Completed
A12: CMP-0011 | B12: Influencer Feb 2024 | C12: Influencer | D12: Retention | E12: Q1 | F12: Feb | G12: 2024-02-01 | H12: 2024-02-28 | I12: 105100 | J12: 86800 | K12: 385599 | L12: 7827 | M12: 95 | N12: 197900 | O12: 127 | P12: =J12/L12 -> 11.089817 | Q12: =IFERROR(J12/M12,0) -> 913.68421 | R12: =L12/K12*100 -> 2.0298289 | S12: =IFERROR(M12/L12*100,0) -> 1.2137473 | T12: =N12/J12 -> 2.2799539 | U12: Completed
A13: CMP-0012 | B13: YouTube Mar 2024 | C13: YouTube | D13: Brand Awareness | E13: Q1 | F13: Mar | G13: 2024-03-01 | H13: 2024-03-28 | I13: 199200 | J13: 191000 | K13: 365714 | L13: 2377 | M13: 44 | N13: 573000 | O13: 68 | P13: =J13/L13 -> 80.353387 | Q13: =IFERROR(J13/M13,0) -> 4340.9091 | R13: =L13/K13*100 -> 0.64996145 | S13: =IFERROR(M13/L13*100,0) -> 1.8510728 | T13: =N13/J13 -> 3 | U13: Completed
... A81: CMP-0080 | B81: Influencer Dec 2024 | C81: Influencer | D81: Lead Generation | E81: Q4 | F81: Dec | G81: 2024-12-01 | H81: 2024-12-28 | I81: 203300 | J81: 182000 | K81: 219308 | L81: 6184 | M81: 62 | N81: 500500 | O81: 121 | P81: =J81/L81 -> 29.430789 | Q81: =IFERROR(J81/M81,0) -> 2935.4839 | R81: =L81/K81*100 -> 2.8197786 | S81: =IFERROR(M81/L81*100,0) -> 1.0025873 | T81: =N81/J81 -> 2.75 | U81: Active

Sheet Channel Performance
A1: 📣 MARKETING CHANNEL PERFORMANCE DASHBOARD — FY 2024
A2: All figures in Indian Rupees (₹) · Source: Campaign Data sheet · Calculated fields auto-update
A4: Channel | B4: Campaigns | C4: Total Budget (₹) | D4: Total Spend (₹) | E4: Budget Util % | F4: Impressions | G4: Clicks | H4: Conversions | I4: Total Revenue (₹) | J4: Avg ROAS | K4: Avg CTR % | L4: Avg Conv Rate %
A5: Google Ads | B5: =COUNTIF('Campaign Data'!C:C,A5) -> 9 | C5: =SUMIF('Campaign Data'!C:C,A5,'Campaign Data'!I:I) -> 1950400 | D5: =SUMIF('Campaign Data'!C:C,A5,'Campaign Data'!J:J) -> 1743600 | E5: =IFERROR(D5/C5,0) -> 0.89397047 | F5: =SUMIF('Campaign Data'!C:C,A5,'Campaign Data'!K:K) -> 3155081 | G5: =SUMIF('Campaign Data'!C:C,A5,'Campaign Data'!L:L) -> 192765 | H5: =SUMIF('Campaign Data'!C:C,A5,'Campaign Data'!M:M) -> 7767 | I5: =SUMIF('Campaign Data'!C:C,A5,'Campaign Data'!N:N) -> 7108900 | J5: =IFERROR(I5/D5,0) -> 4.0771393 | K5: =IFERROR(AVERAGEIF('Campaign Data'!C:C,A5,'Campaign Data'!R:R),0) -> 6.2164252 | L5: =IFERROR(AVERAGEIF('Campaign Data'!C:C,A5,'Campaign Data'!S:S),0) -> 4.0494781
A6: Meta Ads | B6: =COUNTIF('Campaign Data'!C:C,A6) -> 11 | C6: =SUMIF('Campaign Data'!C:C,A6,'Campaign Data'!I:I) -> 2043200 | D6: =SUMIF('Campaign Data'!C:C,A6,'Campaign Data'!J:J) -> 1751600 | E6: =IFERROR(D6/C6,0) -> 0.85728269 | F6: =SUMIF('Campaign Data'!C:C,A6,'Campaign Data'!K:K) -> 4570826 | G6: =SUMIF('Campaign Data'!C:C,A6,'Campaign Data'!L:L) -> 132238 | H6: =SUMIF('Campaign Data'!C:C,A6,'Campaign Data'!M:M) -> 3272 | I6: =SUMIF('Campaign Data'!C:C,A6,'Campaign Data'!N:N) -> 6712800 | J6: =IFERROR(I6/D6,0) -> 3.8323818 | K6: =IFERROR(AVERAGEIF('Campaign Data'!C:C,A6,'Campaign Data'!R:R),0) -> 2.9270988 | L6: =IFERROR(AVERAGEIF('Campaign Data'!C:C,A6,'Campaign Data'!S:S),0) -> 2.5952748
A7: Email | B7: =COUNTIF('Campaign Data'!C:C,A7) -> 11 | C7: =SUMIF('Campaign Data'!C:C,A7,'Campaign Data'!I:I) -> 419000 | D7: =SUMIF('Campaign Data'!C:C,A7,'Campaign Data'!J:J) -> 366000 | E7: =IFERROR(D7/C7,0) -> 0.87350835 | F7: =SUMIF('Campaign Data'!C:C,A7,'Campaign Data'!K:K) -> 2203111 | G7: =SUMIF('Campaign Data'!C:C,A7,'Campaign Data'!L:L) -> 548181 | H7: =SUMIF('Campaign Data'!C:C,A7,'Campaign Data'!M:M) -> 68518 | I7: =SUMIF('Campaign Data'!C:C,A7,'Campaign Data'!N:N) -> 2887400 | J7: =IFERROR(I7/D7,0) -> 7.889071 | K7: =IFERROR(AVERAGEIF('Campaign Data'!C:C,A7,'Campaign Data'!R:R),0) -> 26.127787 | L7: =IFERROR(AVERAGEIF('Campaign Data'!C:C,A7,'Campaign Data'!S:S),0) -> 11.808742
A8: SEO/Organic | B8: =COUNTIF('Campaign Data'!C:C,A8) -> 11 | C8: =SUMIF('Campaign Data'!C:C,A8,'Campaign Data'!I:I) -> 730200 | D8: =SUMIF('Campaign Data'!C:C,A8,'Campaign Data'!J:J) -> 652200 | E8: =IFERROR(D8/C8,0) -> 0.89317995 | F8: =SUMIF('Campaign Data'!C:C,A8,'Campaign Data'!K:K) -> 3964631 | G8: =SUMIF('Campaign Data'!C:C,A8,'Campaign Data'!L:L) -> 173857 | H8: =SUMIF('Campaign Data'!C:C,A8,'Campaign Data'!M:M) -> 6126 | I8: =SUMIF('Campaign Data'!C:C,A8,'Campaign Data'!N:N) -> 4632500 | J8: =IFERROR(I8/D8,0) -> 7.1028826 | K8: =IFERROR(AVERAGEIF('Campaign Data'!C:C,A8,'Campaign Data'!R:R),0) -> 4.140623 | L8: =IFERROR(AVERAGEIF('Campaign Data'!C:C,A8,'Campaign Data'!S:S),0) -> 3.6145584
A9: YouTube | B9: =COUNTIF('Campaign Data'!C:C,A9) -> 10 | C9: =SUMIF('Campaign Data'!C:C,A9,'Campaign Data'!I:I) -> 1810300 | D9: =SUMIF('Campaign Data'!C:C,A9,'Campaign Data'!J:J) -> 1634600 | E9: =IFERROR(D9/C9,0) -> 0.90294426 | F9: =SUMIF('Campaign Data'!C:C,A9,'Campaign Data'!K:K) -> 3971303 | G9: =SUMIF('Campaign Data'!C:C,A9,'Campaign Data'!L:L) -> 39051 | H9: =SUMIF('Campaign Data'!C:C,A9,'Campaign Data'!M:M) -> 545 | I9: =SUMIF('Campaign Data'!C:C,A9,'Campaign Data'!N:N) -> 4730500 | J9: =IFERROR(I9/D9,0) -> 2.8939802 | K9: =IFERROR(AVERAGEIF('Campaign Data'!C:C,A9,'Campaign Data'!R:R),0) -> 1.0918251 | L9: =IFERROR(AVERAGEIF('Campaign Data'!C:C,A9,'Campaign Data'!S:S),0) -> 1.4355933
A10: LinkedIn | B10: =COUNTIF('Campaign Data'!C:C,A10) -> 9 | C10: =SUMIF('Campaign Data'!C:C,A10,'Campaign Data'!I:I) -> 1297500 | D10: =SUMIF('Campaign Data'!C:C,A10,'Campaign Data'!J:J) -> 1139600 | E10: =IFERROR(D10/C10,0) -> 0.87830443 | F10: =SUMIF('Campaign Data'!C:C,A10,'Campaign Data'!K:K) -> 3474949 | G10: =SUMIF('Campaign Data'!C:C,A10,'Campaign Data'!L:L) -> 34813 | H10: =SUMIF('Campaign Data'!C:C,A10,'Campaign Data'!M:M) -> 673 | I10: =SUMIF('Campaign Data'!C:C,A10,'Campaign Data'!N:N) -> 4018400 | J10: =IFERROR(I10/D10,0) -> 3.5261495 | K10: =IFERROR(AVERAGEIF('Campaign Data'!C:C,A10,'Campaign Data'!R:R),0) -> 1.0406533 | L10: =IFERROR(AVERAGEIF('Campaign Data'!C:C,A10,'Campaign Data'!S:S),0) -> 2.0430352
A11: Influencer | B11: =COUNTIF('Campaign Data'!C:C,A11) -> 10 | C11: =SUMIF('Campaign Data'!C:C,A11,'Campaign Data'!I:I) -> 2400400 | D11: =SUMIF('Campaign Data'!C:C,A11,'Campaign Data'!J:J) -> 2146000 | E11: =IFERROR(D11/C11,0) -> 0.89401766 | F11: =SUMIF('Campaign Data'!C:C,A11,'Campaign Data'!K:K) -> 3123817 | G11: =SUMIF('Campaign Data'!C:C,A11,'Campaign Data'!L:L) -> 57471 | H11: =SUMIF('Campaign Data'!C:C,A11,'Campaign Data'!M:M) -> 720 | I11: =SUMIF('Campaign Data'!C:C,A11,'Campaign Data'!N:N) -> 6330700 | J11: =IFERROR(I11/D11,0) -> 2.95 | K11: =IFERROR(AVERAGEIF('Campaign Data'!C:C,A11,'Campaign Data'!R:R),0) -> 1.9247087 | L11: =IFERROR(AVERAGEIF('Campaign Data'!C:C,A11,'Campaign Data'!S:S),0) -> 1.161097
A12: SMS | B12: =COUNTIF('Campaign Data'!C:C,A12) -> 9 | C12: =SUMIF('Campaign Data'!C:C,A12,'Campaign Data'!I:I) -> 148700 | D12: =SUMIF('Campaign Data'!C:C,A12,'Campaign Data'!J:J) -> 127200 | E12: =IFERROR(D12/C12,0) -> 0.85541358 | F12: =SUMIF('Campaign Data'!C:C,A12,'Campaign Data'!K:K) -> 3986182 | G12: =SUMIF('Campaign Data'!C:C,A12,'Campaign Data'!L:L) -> 1281317 | H12: =SUMIF('Campaign Data'!C:C,A12,'Campaign Data'!M:M) -> 83478 | I12: =SUMIF('Campaign Data'!C:C,A12,'Campaign Data'!N:N) -> 721400 | J12: =IFERROR(I12/D12,0) -> 5.6713836 | K12: =IFERROR(AVERAGEIF('Campaign Data'!C:C,A12,'Campaign Data'!R:R),0) -> 32.787713 | L12: =IFERROR(AVERAGEIF('Campaign Data'!C:C,A12,'Campaign Data'!S:S),0) -> 6.3430189
A13: TOTAL / AVG | B13: =SUM(B5:B12) -> 80 | C13: =SUM(C5:C12) -> 10799700 | D13: =SUM(D5:D12) -> 9560800 | E13: =IFERROR(SUM(D5:D12)/SUM(C5:C12),0) -> 0.88528385 | F13: =SUM(F5:F12) -> 28449900 | G13: =SUM(G5:G12) -> 2459693 | H13: =SUM(H5:H12) -> 171099 | I13: =SUM(I5:I12) -> 37142600 | J13: =IFERROR(SUM(I5:I12)/SUM(D5:D12),0) -> 3.8848841 | K13: =AVERAGE(K5:K12) -> 9.5321043 | L13: =AVERAGE(L5:L12) -> 4.1313497

Sheet Monthly Trends
A1: 📅 MONTHLY CAMPAIGN PERFORMANCE TRENDS — FY 2024
A3: Month | B3: Quarter | C3: Campaigns | D3: Budget (₹) | E3: Spend (₹) | F3: Impressions | G3: Clicks | H3: Conversions | I3: Revenue (₹) | J3: Avg ROAS | K3: MoM Rev Δ%
A4: Jan | B4: Q1 | C4: =COUNTIF('Campaign Data'!F:F,A4) -> 6 | D4: =SUMIF('Campaign Data'!F:F,A4,'Campaign Data'!I:I) -> 684000 | E4: =SUMIF('Campaign Data'!F:F,A4,'Campaign Data'!J:J) -> 584800 | F4: =SUMIF('Campaign Data'!F:F,A4,'Campaign Data'!K:K) -> 1699039 | G4: =SUMIF('Campaign Data'!F:F,A4,'Campaign Data'!L:L) -> 299735 | H4: =SUMIF('Campaign Data'!F:F,A4,'Campaign Data'!M:M) -> 19561 | I4: =SUMIF('Campaign Data'!F:F,A4,'Campaign Data'!N:N) -> 2725100 | J4: =IFERROR(I4/E4,0) -> 4.6598837 | K4: =IFERROR(IF(ROW()=4,"-",(I4-I3)/I3),"-") -> -
A5: Feb | B5: Q1 | C5: =COUNTIF('Campaign Data'!F:F,A5) -> 5 | D5: =SUMIF('Campaign Data'!F:F,A5,'Campaign Data'!I:I) -> 754100 | E5: =SUMIF('Campaign Data'!F:F,A5,'Campaign Data'!J:J) -> 673500 | F5: =SUMIF('Campaign Data'!F:F,A5,'Campaign Data'!K:K) -> 2210897 | G5: =SUMIF('Campaign Data'!F:F,A5,'Campaign Data'!L:L) -> 131988 | H5: =SUMIF('Campaign Data'!F:F,A5,'Campaign Data'!M:M) -> 12237 | I5: =SUMIF('Campaign Data'!F:F,A5,'Campaign Data'!N:N) -> 2675300 | J5: =IFERROR(I5/E5,0) -> 3.9722346 | K5: =IFERROR(IF(ROW()=4,"-",(I5-I4)/I4),"-") -> -0.018274559
A6: Mar | B6: Q1 | C6: =COUNTIF('Campaign Data'!F:F,A6) -> 7 | D6: =SUMIF('Campaign Data'!F:F,A6,'Campaign Data'!I:I) -> 925900 | E6: =SUMIF('Campaign Data'!F:F,A6,'Campaign Data'!J:J) -> 807100 | F6: =SUMIF('Campaign Data'!F:F,A6,'Campaign Data'!K:K) -> 2327505 | G6: =SUMIF('Campaign Data'!F:F,A6,'Campaign Data'!L:L) -> 136171 | H6: =SUMIF('Campaign Data'!F:F,A6,'Campaign Data'!M:M) -> 10154 | I6: =SUMIF('Campaign Data'!F:F,A6,'Campaign Data'!N:N) -> 2603600 | J6: =IFERROR(I6/E6,0) -> 3.2258704 | K6: =IFERROR(IF(ROW()=4,"-",(I6-I5)/I5),"-") -> -0.026800733
A7: Apr | B7: Q2 | C7: =COUNTIF('Campaign Data'!F:F,A7) -> 7 | D7: =SUMIF('Campaign Data'!F:F,A7,'Campaign Data'!I:I) -> 1005800 | E7: =SUMIF('Campaign Data'!F:F,A7,'Campaign Data'!J:J) -> 908400 | F7: =SUMIF('Campaign Data'!F:F,A7,'Campaign Data'!K:K) -> 2616455 | G7: =SUMIF('Campaign Data'!F:F,A7,'Campaign Data'!L:L) -> 181575 | H7: =SUMIF('Campaign Data'!F:F,A7,'Campaign Data'!M:M) -> 12583 | I7: =SUMIF('Campaign Data'!F:F,A7,'Campaign Data'!N:N) -> 4022100 | J7: =IFERROR(I7/E7,0) -> 4.427675 | K7: =IFERROR(IF(ROW()=4,"-",(I7-I6)/I6),"-") -> 0.54482255
A8: May | B8: Q2 | C8: =COUNTIF('Campaign Data'!F:F,A8) -> 8 | D8: =SUMIF('Campaign Data'!F:F,A8,'Campaign Data'!I:I) -> 1109500 | E8: =SUMIF('Campaign Data'!F:F,A8,'Campaign Data'!J:J) -> 1057300 | F8: =SUMIF('Campaign Data'!F:F,A8,'Campaign Data'!K:K) -> 2406057 | G8: =SUMIF('Campaign Data'!F:F,A8,'Campaign Data'!L:L) -> 293842 | H8: =SUMIF('Campaign Data'!F:F,A8,'Campaign Data'!M:M) -> 24989 | I8: =SUMIF('Campaign Data'!F:F,A8,'Campaign Data'!N:N) -> 3772800 | J8: =IFERROR(I8/E8,0) -> 3.5683344 | K8: =IFERROR(IF(ROW()=4,"-",(I8-I7)/I7),"-") -> -0.061982546
A9: Jun | B9: Q2 | C9: =COUNTIF('Campaign Data'!F:F,A9) -> 7 | D9: =SUMIF('Campaign Data'!F:F,A9,'Campaign Data'!I:I) -> 930900 | E9: =SUMIF('Campaign Data'!F:F,A9,'Campaign Data'!J:J) -> 878100 | F9: =SUMIF('Campaign Data'!F:F,A9,'Campaign Data'!K:K) -> 2987321 | G9: =SUMIF('Campaign Data'!F:F,A9,'Campaign Data'!L:L) -> 309904 | H9: =SUMIF('Campaign Data'!F:F,A9,'Campaign Data'!M:M) -> 24548 | I9: =SUMIF('Campaign Data'!F:F,A9,'Campaign Data'!N:N) -> 3020200 | J9: =IFERROR(I9/E9,0) -> 3.4394716 | K9: =IFERROR(IF(ROW()=4,"-",(I9-I8)/I8),"-") -> -0.19948049
A10: Jul | B10: Q3 | C10: =COUNTIF('Campaign Data'!F:F,A10) -> 7 | D10: =SUMIF('Campaign Data'!F:F,A10,'Campaign Data'!I:I) -> 1040200 | E10: =SUMIF('Campaign Data'!F:F,A10,'Campaign Data'!J:J) -> 932300 | F10: =SUMIF('Campaign Data'!F:F,A10,'Campaign Data'!K:K) -> 2330792 | G10: =SUMIF('Campaign Data'!F:F,A10,'Campaign Data'!L:L) -> 340103 | H10: =SUMIF('Campaign Data'!F:F,A10,'Campaign Data'!M:M) -> 21659 | I10: =SUMIF('Campaign Data'!F:F,A10,'Campaign Data'!N:N) -> 3829200 | J10: =IFERROR(I10/E10,0) -> 4.1072616 | K10: =IFERROR(IF(ROW()=4,"-",(I10-I9)/I9),"-") -> 0.26786306
A11: Aug | B11: Q3 | C11: =COUNTIF('Campaign Data'!F:F,A11) -> 7 | D11: =SUMIF('Campaign Data'!F:F,A11,'Campaign Data'!I:I) -> 853900 | E11: =SUMIF('Campaign Data'!F:F,A11,'Campaign Data'!J:J) -> 745700 | F11: =SUMIF('Campaign Data'!F:F,A11,'Campaign Data'!K:K) -> 2295351 | G11: =SUMIF('Campaign Data'!F:F,A11,'Campaign Data'!L:L) -> 186125 | H11: =SUMIF('Campaign Data'!F:F,A11,'Campaign Data'!M:M) -> 14560 | I11: =SUMIF('Campaign Data'!F:F,A11,'Campaign Data'!N:N) -> 2555600 | J11: =IFERROR(I11/E11,0) -> 3.4271155 | K11: =IFERROR(IF(ROW()=4,"-",(I11-I10)/I10),"-") -> -0.33260211
A12: Sep | B12: Q3 | C12: =COUNTIF('Campaign Data'!F:F,A12) -> 8 | D12: =SUMIF('Campaign Data'!F:F,A12,'Campaign Data'!I:I) -> 1380600 | E12: =SUMIF('Campaign Data'!F:F,A12,'Campaign Data'!J:J) -> 1146900 | F12: =SUMIF('Campaign Data'!F:F,A12,'Campaign Data'!K:K) -> 3473582 | G12: =SUMIF('Campaign Data'!F:F,A12,'Campaign Data'!L:L) -> 183396 | H12: =SUMIF('Campaign Data'!F:F,A12,'Campaign Data'!M:M) -> 8406 | I12: =SUMIF('Campaign Data'!F:F,A12,'Campaign Data'!N:N) -> 4590300 | J12: =IFERROR(I12/E12,0) -> 4.0023542 | K12: =IFERROR(IF(ROW()=4,"-",(I12-I11)/I11),"-") -> 0.79617311
A13: Oct | B13: Q4 | C13: =COUNTIF('Campaign Data'!F:F,A13) -> 6 | D13: =SUMIF('Campaign Data'!F:F,A13,'Campaign Data'!I:I) -> 624100 | E13: =SUMIF('Campaign Data'!F:F,A13,'Campaign Data'!J:J) -> 567600 | F13: =SUMIF('Campaign Data'!F:F,A13,'Campaign Data'!K:K) -> 1804840 | G13: =SUMIF('Campaign Data'!F:F,A13,'Campaign Data'!L:L) -> 109640 | H13: =SUMIF('Campaign Data'!F:F,A13,'Campaign Data'!M:M) -> 5215 | I13: =SUMIF('Campaign Data'!F:F,A13,'Campaign Data'!N:N) -> 1961300 | J13: =IFERROR(I13/E13,0) -> 3.4554264 | K13: =IFERROR(IF(ROW()=4,"-",(I13-I12)/I12),"-") -> -0.57272945
A14: Nov | B14: Q4 | C14: =COUNTIF('Campaign Data'!F:F,A14) -> 7 | D14: =SUMIF('Campaign Data'!F:F,A14,'Campaign Data'!I:I) -> 867700 | E14: =SUMIF('Campaign Data'!F:F,A14,'Campaign Data'!J:J) -> 684200 | F14: =SUMIF('Campaign Data'!F:F,A14,'Campaign Data'!K:K) -> 2622643 | G14: =SUMIF('Campaign Data'!F:F,A14,'Campaign Data'!L:L) -> 204382 | H14: =SUMIF('Campaign Data'!F:F,A14,'Campaign Data'!M:M) -> 14583 | I14: =SUMIF('Campaign Data'!F:F,A14,'Campaign Data'!N:N) -> 3220100 | J14: =IFERROR(I14/E14,0) -> 4.7063724 | K14: =IFERROR(IF(ROW()=4,"-",(I14-I13)/I13),"-") -> 0.6418192
A15: Dec | B15: Q4 | C15: =COUNTIF('Campaign Data'!F:F,A15) -> 5 | D15: =SUMIF('Campaign Data'!F:F,A15,'Campaign Data'!I:I) -> 623000 | E15: =SUMIF('Campaign Data'!F:F,A15,'Campaign Data'!J:J) -> 574900 | F15: =SUMIF('Campaign Data'!F:F,A15,'Campaign Data'!K:K) -> 1675418 | G15: =SUMIF('Campaign Data'!F:F,A15,'Campaign Data'!L:L) -> 82832 | H15: =SUMIF('Campaign Data'!F:F,A15,'Campaign Data'!M:M) -> 2604 | I15: =SUMIF('Campaign Data'!F:F,A15,'Campaign Data'!N:N) -> 2167000 | J15: =IFERROR(I15/E15,0) -> 3.7693512 | K15: =IFERROR(IF(ROW()=4,"-",(I15-I14)/I14),"-") -> -0.32703953
A16: FULL YEAR TOTAL | C16: =SUM(C4:C15) -> 80 | D16: =SUM(D4:D15) -> 10799700 | E16: =SUM(E4:E15) -> 9560800 | F16: =SUM(F4:F15) -> 28449900 | G16: =SUM(G4:G15) -> 2459693 | H16: =SUM(H4:H15) -> 171099 | I16: =SUM(I4:I15) -> 37142600 | J16: =IFERROR(SUM(I4:I15)/SUM(E4:E15),0) -> 3.8848841 | K16: —

Sheet Objective Analysis
A1: 🎯 CAMPAIGN OBJECTIVE & FUNNEL ANALYSIS — FY 2024
A3: Performance by Campaign Objective
A4: Objective | B4: Campaigns | C4: Budget (₹) | D4: Spend (₹) | E4: Leads | F4: Conversions | G4: Revenue (₹) | H4: ROAS | I4: CPL (₹) | J4: CPA (₹)
A5: Brand Awareness | B5: =COUNTIF('Campaign Data'!D:D,A5) -> 19 | C5: =SUMIF('Campaign Data'!D:D,A5,'Campaign Data'!I:I) -> 2598200 | D5: =SUMIF('Campaign Data'!D:D,A5,'Campaign Data'!J:J) -> 2340100 | E5: =SUMIF('Campaign Data'!D:D,A5,'Campaign Data'!O:O) -> 92616 | F5: =SUMIF('Campaign Data'!D:D,A5,'Campaign Data'!M:M) -> 59052 | G5: =SUMIF('Campaign Data'!D:D,A5,'Campaign Data'!N:N) -> 9161900 | H5: =IFERROR(G5/D5,0) -> 3.9151746 | I5: =IFERROR(D5/E5,0) -> 25.266693 | J5: =IFERROR(D5/F5,0) -> 39.627786
A6: Lead Generation | B6: =COUNTIF('Campaign Data'!D:D,A6) -> 14 | C6: =SUMIF('Campaign Data'!D:D,A6,'Campaign Data'!I:I) -> 2544400 | D6: =SUMIF('Campaign Data'!D:D,A6,'Campaign Data'!J:J) -> 2265600 | E6: =SUMIF('Campaign Data'!D:D,A6,'Campaign Data'!O:O) -> 32983 | F6: =SUMIF('Campaign Data'!D:D,A6,'Campaign Data'!M:M) -> 13196 | G6: =SUMIF('Campaign Data'!D:D,A6,'Campaign Data'!N:N) -> 8821600 | H6: =IFERROR(G6/D6,0) -> 3.8937147 | I6: =IFERROR(D6/E6,0) -> 68.689931 | J6: =IFERROR(D6/F6,0) -> 171.68839
A7: Conversions | B7: =COUNTIF('Campaign Data'!D:D,A7) -> 14 | C7: =SUMIF('Campaign Data'!D:D,A7,'Campaign Data'!I:I) -> 1348600 | D7: =SUMIF('Campaign Data'!D:D,A7,'Campaign Data'!J:J) -> 1196300 | E7: =SUMIF('Campaign Data'!D:D,A7,'Campaign Data'!O:O) -> 77953 | F7: =SUMIF('Campaign Data'!D:D,A7,'Campaign Data'!M:M) -> 40090 | G7: =SUMIF('Campaign Data'!D:D,A7,'Campaign Data'!N:N) -> 5259000 | H7: =IFERROR(G7/D7,0) -> 4.3960545 | I7: =IFERROR(D7/E7,0) -> 15.346427 | J7: =IFERROR(D7/F7,0) -> 29.840359
A8: Retention | B8: =COUNTIF('Campaign Data'!D:D,A8) -> 18 | C8: =SUMIF('Campaign Data'!D:D,A8,'Campaign Data'!I:I) -> 2288500 | D8: =SUMIF('Campaign Data'!D:D,A8,'Campaign Data'!J:J) -> 2012800 | E8: =SUMIF('Campaign Data'!D:D,A8,'Campaign Data'!O:O) -> 62450 | F8: =SUMIF('Campaign Data'!D:D,A8,'Campaign Data'!M:M) -> 28237 | G8: =SUMIF('Campaign Data'!D:D,A8,'Campaign Data'!N:N) -> 6893500 | H8: =IFERROR(G8/D8,0) -> 3.4248311 | I8: =IFERROR(D8/E8,0) -> 32.230584 | J8: =IFERROR(D8/F8,0) -> 71.28236
A9: Traffic | B9: =COUNTIF('Campaign Data'!D:D,A9) -> 15 | C9: =SUMIF('Campaign Data'!D:D,A9,'Campaign Data'!I:I) -> 2020000 | D9: =SUMIF('Campaign Data'!D:D,A9,'Campaign Data'!J:J) -> 1746000 | E9: =SUMIF('Campaign Data'!D:D,A9,'Campaign Data'!O:O) -> 69258 | F9: =SUMIF('Campaign Data'!D:D,A9,'Campaign Data'!M:M) -> 30524 | G9: =SUMIF('Campaign Data'!D:D,A9,'Campaign Data'!N:N) -> 7006600 | H9: =IFERROR(G9/D9,0) -> 4.0129439 | I9: =IFERROR(D9/E9,0) -> 25.210084 | J9: =IFERROR(D9/F9,0) -> 57.200891
A10: TOTAL | B10: =SUM(B5:B9) -> 80 | C10: =SUM(C5:C9) -> 10799700 | D10: =SUM(D5:D9) -> 9560800 | E10: =SUM(E5:E9) -> 335260 | F10: =SUM(F5:F9) -> 171099 | G10: =SUM(G5:G9) -> 37142600 | H10: =IFERROR(SUM(G5:G9)/SUM(D5:D9),0) -> 3.8848841 | I10: =IFERROR(SUM(D5:D9)/SUM(E5:E9),0) -> 28.517568 | J10: =IFERROR(SUM(D5:D9)/SUM(F5:F9),0) -> 55.87876
A30: Conversion Funnel Metrics by Channel
A31: Channel | B31: Impressions | C31: Clicks | D31: Leads | E31: Conversions | F31: Impr→Click% | G31: Click→Lead% | H31: Lead→Conv% | I31: Overall Conv%
A32: Google Ads | B32: =SUMIF('Campaign Data'!C:C,A32,'Campaign Data'!K:K) -> 3155081 | C32: =SUMIF('Campaign Data'!C:C,A32,'Campaign Data'!L:L) -> 192765 | D32: =SUMIF('Campaign Data'!C:C,A32,'Campaign Data'!O:O) -> 16173 | E32: =SUMIF('Campaign Data'!C:C,A32,'Campaign Data'!M:M) -> 7767 | F32: =IFERROR(C32/B32*100,0) -> 6.1096688 | G32: =IFERROR(D32/C32*100,0) -> 8.3900086 | H32: =IFERROR(E32/D32*100,0) -> 48.024485 | I32: =IFERROR(E32/B32*100,0) -> 0.24617435
A33: Meta Ads | B33: =SUMIF('Campaign Data'!C:C,A33,'Campaign Data'!K:K) -> 4570826 | C33: =SUMIF('Campaign Data'!C:C,A33,'Campaign Data'!L:L) -> 132238 | D33: =SUMIF('Campaign Data'!C:C,A33,'Campaign Data'!O:O) -> 7968 | E33: =SUMIF('Campaign Data'!C:C,A33,'Campaign Data'!M:M) -> 3272 | F33: =IFERROR(C33/B33*100,0) -> 2.8930876 | G33: =IFERROR(D33/C33*100,0) -> 6.0254995 | H33: =IFERROR(E33/D33*100,0) -> 41.064257 | I33: =IFERROR(E33/B33*100,0) -> 0.071584436
A34: Email | B34: =SUMIF('Campaign Data'!C:C,A34,'Campaign Data'!K:K) -> 2203111 | C34: =SUMIF('Campaign Data'!C:C,A34,'Campaign Data'!L:L) -> 548181 | D34: =SUMIF('Campaign Data'!C:C,A34,'Campaign Data'!O:O) -> 125329 | E34: =SUMIF('Campaign Data'!C:C,A34,'Campaign Data'!M:M) -> 68518 | F34: =IFERROR(C34/B34*100,0) -> 24.882133 | G34: =IFERROR(D34/C34*100,0) -> 22.862704 | H34: =IFERROR(E34/D34*100,0) -> 54.670507 | I34: =IFERROR(E34/B34*100,0) -> 3.1100566
A35: SEO/Organic | B35: =SUMIF('Campaign Data'!C:C,A35,'Campaign Data'!K:K) -> 3964631 | C35: =SUMIF('Campaign Data'!C:C,A35,'Campaign Data'!L:L) -> 173857 | D35: =SUMIF('Campaign Data'!C:C,A35,'Campaign Data'!O:O) -> 15833 | E35: =SUMIF('Campaign Data'!C:C,A35,'Campaign Data'!M:M) -> 6126 | F35: =IFERROR(C35/B35*100,0) -> 4.3852 | G35: =IFERROR(D35/C35*100,0) -> 9.1069097 | H35: =IFERROR(E35/D35*100,0) -> 38.691341 | I35: =IFERROR(E35/B35*100,0) -> 0.15451627
A36: YouTube | B36: =SUMIF('Campaign Data'!C:C,A36,'Campaign Data'!K:K) -> 3971303 | C36: =SUMIF('Campaign Data'!C:C,A36,'Campaign Data'!L:L) -> 39051 | D36: =SUMIF('Campaign Data'!C:C,A36,'Campaign Data'!O:O) -> 1136 | E36: =SUMIF('Campaign Data'!C:C,A36,'Campaign Data'!M:M) -> 545 | F36: =IFERROR(C36/B36*100,0) -> 0.98332965 | G36: =IFERROR(D36/C36*100,0) -> 2.9090164 | H36: =IFERROR(E36/D36*100,0) -> 47.975352 | I36: =IFERROR(E36/B36*100,0) -> 0.013723456
A37: LinkedIn | B37: =SUMIF('Campaign Data'!C:C,A37,'Campaign Data'!K:K) -> 3474949 | C37: =SUMIF('Campaign Data'!C:C,A37,'Campaign Data'!L:L) -> 34813 | D37: =SUMIF('Campaign Data'!C:C,A37,'Campaign Data'!O:O) -> 1653 | E37: =SUMIF('Campaign Data'!C:C,A37,'Campaign Data'!M:M) -> 673 | F37: =IFERROR(C37/B37*100,0) -> 1.0018277 | G37: =IFERROR(D37/C37*100,0) -> 4.7482262 | H37: =IFERROR(E37/D37*100,0) -> 40.713854 | I37: =IFERROR(E37/B37*100,0) -> 0.019367191
A38: Influencer | B38: =SUMIF('Campaign Data'!C:C,A38,'Campaign Data'!K:K) -> 3123817 | C38: =SUMIF('Campaign Data'!C:C,A38,'Campaign Data'!L:L) -> 57471 | D38: =SUMIF('Campaign Data'!C:C,A38,'Campaign Data'!O:O) -> 1636 | E38: =SUMIF('Campaign Data'!C:C,A38,'Campaign Data'!M:M) -> 720 | F38: =IFERROR(C38/B38*100,0) -> 1.8397685 | G38: =IFERROR(D38/C38*100,0) -> 2.8466531 | H38: =IFERROR(E38/D38*100,0) -> 44.00978 | I38: =IFERROR(E38/B38*100,0) -> 0.023048725
A39: SMS | B39: =SUMIF('Campaign Data'!C:C,A39,'Campaign Data'!K:K) -> 3986182 | C39: =SUMIF('Campaign Data'!C:C,A39,'Campaign Data'!L:L) -> 1281317 | D39: =SUMIF('Campaign Data'!C:C,A39,'Campaign Data'!O:O) -> 165532 | E39: =SUMIF('Campaign Data'!C:C,A39,'Campaign Data'!M:M) -> 83478 | F39: =IFERROR(C39/B39*100,0) -> 32.143966 | G39: =IFERROR(D39/C39*100,0) -> 12.918895 | H39: =IFERROR(E39/D39*100,0) -> 50.430128 | I39: =IFERROR(E39/B39*100,0) -> 2.0941844
